README.md
setup.cfg
setup.py
ss_distspacepkg/Binomialdistribution.py
ss_distspacepkg/Gaussiandistribution.py
ss_distspacepkg/Generaldistribution.py
ss_distspacepkg/__init__.py
ss_distspacepkg.egg-info/PKG-INFO
ss_distspacepkg.egg-info/SOURCES.txt
ss_distspacepkg.egg-info/dependency_links.txt
ss_distspacepkg.egg-info/not-zip-safe
ss_distspacepkg.egg-info/top_level.txt